gdrive_filesys/__init__.py
gdrive_filesys/attr.py
gdrive_filesys/cli.py
gdrive_filesys/color.py
gdrive_filesys/common.py
gdrive_filesys/config.py
gdrive_filesys/default_config.toml
gdrive_filesys/directories.py
gdrive_filesys/error.py
gdrive_filesys/eventq.py
gdrive_filesys/filesystem.py
gdrive_filesys/gdcreate.py
gdrive_filesys/gddelete.py
gdrive_filesys/gddownload.py
gdrive_filesys/gdupload.py
gdrive_filesys/gitignore.py
gdrive_filesys/heartbeat.py
gdrive_filesys/localonly.py
gdrive_filesys/lock.py
gdrive_filesys/log.py
gdrive_filesys/metrics.py
gdrive_filesys/mimetype.py
gdrive_filesys/oauth.py
gdrive_filesys/refresh.py
gdrive_filesys/rpc.py
gdrive_filesys/api/__init__.py
gdrive_filesys/api/api.py
gdrive_filesys/api/chmod.py
gdrive_filesys/api/chown.py
gdrive_filesys/api/create.py
gdrive_filesys/api/getxattr.py
gdrive_filesys/api/mkdir.py
gdrive_filesys/api/readchunk.py
gdrive_filesys/api/readdir.py
gdrive_filesys/api/readlink.py
gdrive_filesys/api/remove.py
gdrive_filesys/api/rename.py
gdrive_filesys/api/rmdir.py
gdrive_filesys/api/symlink.py
gdrive_filesys/api/truncate.py
gdrive_filesys/api/utime.py
gdrive_filesys/api/writefile.py
gdrive_filesys/cache/data.py
gdrive_filesys/cache/db.py
gdrive_filesys/cache/mem.py
gdrive_filesys/cache/metadata.py
gdrive_filesys/cache/refreshcache.py
gdrive_filesys-0.0.7.dist-info/licenses/LICENSE
gdrive_filesys-0.0.7.dist-info/METADATA
gdrive_filesys-0.0.7.dist-info/WHEEL
gdrive_filesys-0.0.7.dist-info/entry_points.txt
gdrive_filesys-0.0.7.dist-info/top_level.txt
gdrive_filesys-0.0.7.dist-info/RECORD
