Metadata-Version: 2.4
Name: gdrive-filesys
Version: 0.0.7
Summary: gdrive-filesys is a Linux or macOS filesystem for Google Drive.
Author-email: Dave Christenson <davechri58@gmail.com>
License: MIT
Project-URL: Repository, https://github.com/davechri/gdrive-filesys
Project-URL: Issues, https://github.com/davechri/gdrive-filesys/issues
Keywords: google,drive,fuse-filesystem,fuse,offline,cache,git
Classifier: Development Status :: 4 - Beta
Classifier: Topic :: System :: Filesystems
Classifier: Development Status :: 4 - Beta
Classifier: Intended Audience :: Developers
Classifier: Intended Audience :: End Users/Desktop
Classifier: Operating System :: MacOS :: MacOS X
Classifier: Operating System :: POSIX :: Linux
Classifier: Programming Language :: Python
Classifier: Programming Language :: Python :: 2.7
Classifier: Programming Language :: Python :: 3.3
Classifier: Programming Language :: Python :: 3.4
Classifier: Programming Language :: Python :: 3.5
Classifier: Programming Language :: Python :: Implementation :: PyPy
Classifier: License :: OSI Approved :: MIT License
License-File: LICENSE
Requires-Dist: fusepy==3.0.1
Requires-Dist: requests==2.32.5
Requires-Dist: plyvel==1.5.1
Requires-Dist: python-dateutil==2.9.0.post0
Requires-Dist: google-api-python-client==2.187.0
Requires-Dist: google-auth-oauthlib==1.2.3
Requires-Dist: gitignore_parser==0.1.13
Requires-Dist: humanize==4.15.0
Dynamic: license-file
